flash_validator/__init__.py
flash_validator/condition.py
flash_validator/error.py
flash_validator/rule.py
flash_validator/source.py
flash_validator/extra_source/__init__.py
flash_validator/extra_source/flask.py
flash_validator-1.0.0.dist-info/DESCRIPTION.rst
flash_validator-1.0.0.dist-info/METADATA
flash_validator-1.0.0.dist-info/RECORD
flash_validator-1.0.0.dist-info/WHEEL
flash_validator-1.0.0.dist-info/metadata.json
flash_validator-1.0.0.dist-info/top_level.txt
