Metadata-Version: 2.0
Name: flash-validator
Version: 1.0.0
Summary: simple python data validation
Home-page: https://github.com/ketu/flash_validator
Author: ketu.lai
Author-email: ketu.lai@gmail.com
License: MIT
Keywords: python data validation
Platform: UNKNOWN
